teidocument/__init__.py
teidocument/teidoc.py
teidocument-1.0.9.dist-info/LICENSE
teidocument-1.0.9.dist-info/WHEEL
teidocument-1.0.9.dist-info/METADATA
teidocument-1.0.9.dist-info/RECORD
